sk8ai/__init__.py
sk8ai/maths.py
sk8ai/sk8.py
sk8ai-1.3.dist-info/METADATA
sk8ai-1.3.dist-info/WHEEL
sk8ai-1.3.dist-info/top_level.txt
sk8ai-1.3.dist-info/RECORD
